tpds_extension/ecc204_support/extension.yaml
tpds_extension/ecc204_support/setup.py
tpds_extension/ecc204_support/version.py
tpds_extension/ecc204_support/backend/__init__.py
tpds_extension/ecc204_support/backend/msg_handler.py
tpds_extension/ecc204_support/backend/symm_auth_user_inputs.py
tpds_extension/ecc204_support/backend/wpc_user_inputs.py
tpds_extension/ecc204_support/backend/api/__init__.py
tpds_extension/ecc204_support/backend/api/apis.py
tpds_extension/ecc204_support/backend/api/ecc204.py
tpds_extension/ecc204_support/backend/api/ecc204_xml_updates.py
tpds_extension/ecc204_support/backend/api/models.py
tpds_extension/ecc204_support/backend/api/tflxauth_ecc204.py
tpds_extension/ecc204_support/backend/api/tflxwpc_ecc204.py
tpds_extension/ecc204_support/backend/api/base/ECC204_TA010_base.xml
tpds_extension/ecc204_support/backend/parts/ecc204.yaml
tpds_extension/ecc204_support/backend/parts/ecc206.yaml
tpds_extension/ecc204_support/frontend/TrustFlex/ECC204-AsymmetricAuthentication.ipynb
tpds_extension/ecc204_support/frontend/TrustFlex/ECC204-JSON-Auth.ipynb
tpds_extension/ecc204_support/frontend/TrustFlex/ECC204-SymmetricAuthentication.ipynb
tpds_extension/ecc204_support/frontend/TrustFlex/ECC204-WPC-Authentication.ipynb
tpds_extension/ecc204_support/frontend/TrustFlex/cust_def_device.c
tpds_extension/ecc204_support/frontend/TrustFlex/cust_def_device.h
tpds_extension/ecc204_support/frontend/TrustFlex/cust_def_signer.c
tpds_extension/ecc204_support/frontend/TrustFlex/cust_def_signer.h
tpds_extension/ecc204_support/frontend/TrustFlex/default_json_message.json
tpds_extension/ecc204_support/frontend/TrustFlex/ecc204_tflxwpc.h
tpds_extension/ecc204_support/frontend/TrustFlex/firmware.zip
tpds_extension/ecc204_support/frontend/TrustFlex/project_config.h
tpds_extension/ecc204_support/frontend/TrustFlex/assets/ECC204_AsymmAuth.md
tpds_extension/ecc204_support/frontend/TrustFlex/assets/ECC204_JSON_Auth.md
tpds_extension_ecc204_support-2.0.0.dist-info/METADATA
tpds_extension_ecc204_support-2.0.0.dist-info/WHEEL
tpds_extension_ecc204_support-2.0.0.dist-info/top_level.txt
tpds_extension_ecc204_support-2.0.0.dist-info/RECORD
