Metadata-Version: 2.4
Name: tpds-extension-ecc204-support
Version: 2.0.0
Summary: Microchip(SPG) Trust Platform - ECC204 Device Support
Home-page: https://www.microchip.com/TrustPlatform
Author: Microchip Technology
Author-email: SPG.Tools@microchip.com
Classifier: License :: Other/Proprietary License
Classifier: Development Status :: 4 - Beta
Classifier: Programming Language :: Python :: 3
Classifier: Operating System :: OS Independent
Requires-Python: >=3.6
Requires-Dist: tpds-core>=2.3.4
Requires-Dist: tpds-helper>=2.3.6
